RumusMatematika.py
testicles-0.1.0.dist-info/METADATA
testicles-0.1.0.dist-info/WHEEL
testicles-0.1.0.dist-info/top_level.txt
testicles-0.1.0.dist-info/RECORD
